xia_logger/__init__.py
xia_logger/logger.cpython-39-darwin.so
xia_logger-0.1.6.dist-info/LICENSE.txt
xia_logger-0.1.6.dist-info/METADATA
xia_logger-0.1.6.dist-info/WHEEL
xia_logger-0.1.6.dist-info/top_level.txt
xia_logger-0.1.6.dist-info/RECORD
