Metadata-Version: 2.1
Name: xia-logger
Version: 0.1.6
Summary: UNKNOWN
Home-page: https://develop.x-i-a.com/docs/xia-logger/0.1.6/index.html
Author: X-I-A
Author-email: admin@x-i-a.com
License: UNKNOWN
Platform: UNKNOWN
Requires-Python: >=3.9
License-File: LICENSE.txt
Requires-Dist: xia-engine
Requires-Dist: xia-coder
Requires-Dist: xia-storer
Requires-Dist: xia-models
